net_math_init/__init__.py
watts_net_math/__init__.py
watts_net_math-0.0.2.dist-info/LICENSE
watts_net_math-0.0.2.dist-info/METADATA
watts_net_math-0.0.2.dist-info/WHEEL
watts_net_math-0.0.2.dist-info/top_level.txt
watts_net_math-0.0.2.dist-info/RECORD
