Metadata-Version: 2.1
Name: watts-net-math
Version: 0.0.2
Summary: A package with methods to help with IP address subnetting.
Home-page: https://github.com/slickwatts/net_math.git
Author: Tyler Watts
Author-email: slickwattsbiz@gmail.com
License: MIT
Platform: UNKNOWN
Requires-Python: >=3.8
License-File: LICENSE
